sysmontask/__init__.py
sysmontask/disk.py
sysmontask/gi_composites.py
sysmontask/gpu.py
sysmontask/mem.py
sysmontask/move.sh
sysmontask/net.py
sysmontask/proc-kill.sh
sysmontask/proc.py
sysmontask/proc_cinnamon.py
sysmontask/proc_xfce.py
sysmontask/rooter.py
sysmontask/rooter_default.py
sysmontask/sidepane.py
sysmontask/sysmontask.py
sysmontask/theme_setter.py
sysmontask/uninstall_for_pip.sh
sysmontask/__pycache__/disk.cpython-38.pyc
sysmontask/__pycache__/gi_composites.cpython-38.pyc
sysmontask/__pycache__/gpu.cpython-38.pyc
sysmontask/__pycache__/mem.cpython-38.pyc
sysmontask/__pycache__/net.cpython-38.pyc
sysmontask/__pycache__/proc.cpython-38.pyc
sysmontask/__pycache__/rooter.cpython-38.pyc
sysmontask/__pycache__/sidepane.cpython-38.pyc
sysmontask/__pycache__/sysmontask.cpython-38.pyc
usr/share/applications/SysMonTask.desktop
usr/share/doc/sysmontask/AUTHORS
usr/share/doc/sysmontask/LICENSE
usr/share/doc/sysmontask/README.md
usr/share/sysmontask/glade_files/disk.glade
usr/share/sysmontask/glade_files/diskSidepane.glade
usr/share/sysmontask/glade_files/gpu.glade
usr/share/sysmontask/glade_files/gpuSidepane.glade
usr/share/sysmontask/glade_files/net.glade
usr/share/sysmontask/glade_files/netSidepane.glade
usr/share/sysmontask/glade_files/sysmontask.glade
usr/share/sysmontask/icons/SysMonTask.png
sysmontask-1.1.1b25.dist-info/AUTHORS
sysmontask-1.1.1b25.dist-info/LICENSE
sysmontask-1.1.1b25.dist-info/METADATA
sysmontask-1.1.1b25.dist-info/WHEEL
sysmontask-1.1.1b25.dist-info/entry_points.txt
sysmontask-1.1.1b25.dist-info/top_level.txt
sysmontask-1.1.1b25.dist-info/RECORD
