Metadata-Version: 2.1
Name: sysmontask
Version: 1.1.1b25
Summary: System Monitor With UI Like Windows
Home-page: https://github.com/KrispyCamel4u/SysMonTask
Author: Neeraj Kumar
Author-email: neerajjangra4u@gmail.com
License: BSD-3
Platform: UNKNOWN
Classifier: Programming Language :: Python :: 3
Classifier: License :: OSI Approved :: BSD License
Classifier: Operating System :: POSIX :: Linux
Classifier: Topic :: System :: Monitoring
Requires-Dist: PyGObject
Requires-Dist: psutil (>=5.7.2)
Requires-Dist: pycairo
